[
  {
    "name": "BUNZL PLC ORD 32 1/7P",
    "percentageChange": 5.2,
    "marketCap": 7811580000
  },
  {
    "name": "FRESNILLO PLC ORD USD0.50",
    "percentageChange": 1.84,
    "marketCap": 12446130000
  },
  {
    "name": "BABCOCK INTERNATIONAL GROUP PLC ORD 60P",
    "percentageChange": 1.4,
    "marketCap": 5040750000
  },
  {
    "name": "ENDEAVOUR MINING PLC ORD USD0.01",
    "percentageChange": 1.33,
    "marketCap": 6164280000
  },
  {
    "name": "SHELL PLC ORD EUR0.07",
    "percentageChange": 1.11,
    "marketCap": 157500250000
  },
  {
    "name": "BT GROUP PLC ORD 5P",
    "percentageChange": 0.99,
    "marketCap": 21239400000
  },
  {
    "name": "TESCO PLC ORD 6 1/3P",
    "percentageChange": 0.96,
    "marketCap": 27863220000
  },
  {
    "name": "ANGLO AMERICAN PLC ORD USD0.623855311355311",
    "percentageChange": 0.95,
    "marketCap": 25928890000
  },
  {
    "name": "ANTOFAGASTA PLC ORD 5P",
    "percentageChange": 0.74,
    "marketCap": 21363510000
  },
  {
    "name": "ASHTEAD GROUP PLC ORD 10P",
    "percentageChange": 0.62,
    "marketCap": 23189970000
  },
  {
    "name": "ASTRAZENECA PLC ORD SHS $0.25",
    "percentageChange": 0.62,
    "marketCap": 185585690000
  },
  {
    "name": "BAE SYSTEMS PLC ORD 2.5P",
    "percentageChange": 0.57,
    "marketCap": 53057810000
  },
  {
    "name": "ROLLS-ROYCE HOLDINGS PLC ORD SHS 20P",
    "percentageChange": 0.48,
    "marketCap": 87973250000
  },
  {
    "name": "SAINSBURY(J) PLC ORD 28 4/7P",
    "percentageChange": 0.46,
    "marketCap": 6973190000
  },
  {
    "name": "HALMA PLC ORD 10P",
    "percentageChange": 0.37,
    "marketCap": 12376440000
  },
  {
    "name": "DIPLOMA PLC ORD 5P",
    "percentageChange": 0.28,
    "marketCap": 7285770000
  },
  {
    "name": "BP PLC $0.25",
    "percentageChange": 0.21,
    "marketCap": 66920600000.00001
  },
  {
    "name": "GSK PLC ORD 31 1/4P",
    "percentageChange": 0.2,
    "marketCap": 60248610000
  },
  {
    "name": "CRODA INTERNATIONAL PLC ORD 10.609756P",
    "percentageChange": 0.16,
    "marketCap": 3566290000
  },
  {
    "name": "HIKMA PHARMACEUTICALS PLC ORD SHS 10P",
    "percentageChange": null,
    "marketCap": 4073840000
  },
  {
    "name": "EXPERIAN PLC ORD USD0.10",
    "percentageChange": -1.55,
    "marketCap": 35510830000
  },
  {
    "name": "GLENCORE PLC ORD USD0.01",
    "percentageChange": -0.31,
    "marketCap": 35014610000
  },
  {
    "name": "STANDARD CHARTERED PLC ORD USD0.50",
    "percentageChange": -2.61,
    "marketCap": 32703230000
  },
  {
    "name": "HALEON PLC ORD GBP0.01",
    "percentageChange": -0.44,
    "marketCap": 32684040000
  },
  {
    "name": "COCA-COLA EUROPACIFIC PARTNERS PLC ORD EUR0.01 (DI)",
    "percentageChange": -0.75,
    "marketCap": 30601990000
  },
  {
    "name": "TESCO PLC ORD 6 1/3P",
    "percentageChange": 0.96,
    "marketCap": 27863220000
  },
  {
    "name": "ANGLO AMERICAN PLC ORD USD0.623855311355311",
    "percentageChange": 0.95,
    "marketCap": 25928890000
  },
  {
    "name": "PRUDENTIAL PLC ORD 5P",
    "percentageChange": -1.98,
    "marketCap": 25700700000
  },
  {
    "name": "IMPERIAL BRANDS PLC ORD 10P",
    "percentageChange": -0.22,
    "marketCap": 25256760000
  },
  {
    "name": "ASHTEAD GROUP PLC ORD 10P",
    "percentageChange": 0.62,
    "marketCap": 23189970000
  },
  {
    "name": "VODAFONE GROUP PLC ORD USD0.20 20/21",
    "percentageChange": -0.86,
    "marketCap": 21390070000
  },
  {
    "name": "ANTOFAGASTA PLC ORD 5P",
    "percentageChange": 0.74,
    "marketCap": 21363510000
  },
  {
    "name": "BT GROUP PLC ORD 5P",
    "percentageChange": 0.99,
    "marketCap": 21239400000
  },
  {
    "name": "AVIVA PLC ORD 32 17/19P",
    "percentageChange": -0.51,
    "marketCap": 20561740000
  },
  {
    "name": "SSE PLC ORD 50P",
    "percentageChange": -0.33,
    "marketCap": 19851370000
  },
  {
    "name": "INTL CONSOLIDATED AIRLINES GROUP SA ORD EUR0.10 (CDI)",
    "percentageChange": -0.61,
    "marketCap": 18278760000
  },
  {
    "name": "ASSOCIATED BRITISH FOODS PLC ORD 5 15/22P",
    "percentageChange": -3.89,
    "marketCap": 16568099999.999998
  },
  {
    "name": "NEXT PLC ORD 10P",
    "percentageChange": -0.37,
    "marketCap": 15000900000
  },
  {
    "name": "LEGAL & GENERAL GROUP PLC ORD 2 1/2P",
    "percentageChange": -0.94,
    "marketCap": 14654970000
  },
  {
    "name": "COCA-COLA HBC AG ORD CHF6.70 (CDI)",
    "percentageChange": -1.9,
    "marketCap": 14147730000
  },
  {
    "name": "INTERCONTINENTAL HOTELS GROUP PLC ORD 20 340/399P",
    "percentageChange": -1.68,
    "marketCap": 13751720000
  },
  {
    "name": "SCOTTISH MORTGAGE INV TST PLC ORD 5P",
    "percentageChange": -0.14,
    "marketCap": 12450070000
  },
  {
    "name": "FRESNILLO PLC ORD USD0.50",
    "percentageChange": 1.84,
    "marketCap": 12446130000
  },
  {
    "name": "HALMA PLC ORD 10P",
    "percentageChange": 0.37,
    "marketCap": 12376440000
  },
  {
    "name": "SMITH & NEPHEW PLC ORD USD0.20",
    "percentageChange": -0.04,
    "marketCap": 12065980000
  },
  {
    "name": "INFORMA PLC ORD 0.1P",
    "percentageChange": -1.21,
    "marketCap": 11581690000
  },
  {
    "name": "ADMIRAL GROUP PLC ORD 0.1P",
    "percentageChange": -1.15,
    "marketCap": 11198500000
  },
  {
    "name": "THE SAGE GROUP PLC ORD 1 4/77P",
    "percentageChange": -1.95,
    "marketCap": 10607340000
  },
  {
    "name": "RENTOKIL INITIAL PLC ORD 1P",
    "percentageChange": -2.18,
    "marketCap": 9159420000
  },
  {
    "name": "SEGRO PLC ORD 10P",
    "percentageChange": -1.3,
    "marketCap": 8754380000
  },
  {
    "name": "AIRTEL AFRICA PLC ORD USD0.50",
    "percentageChange": -1.01,
    "marketCap": 7969010000
  },
  {
    "name": "UNITED UTILITIES GROUP PLC ORD 5P",
    "percentageChange": -0.09,
    "marketCap": 7954230000
  },
  {
    "name": "CENTRICA PLC ORD 6 14/81P",
    "percentageChange": -0.88,
    "marketCap": 7929250000
  },
  {
    "name": "SEVERN TRENT PLC ORD 97 17/19P",
    "percentageChange": -0.53,
    "marketCap": 7886600000
  },
  {
    "name": "BUNZL PLC ORD 32 1/7P",
    "percentageChange": 5.2,
    "marketCap": 7811580000
  },
  {
    "name": "SMITHS GROUP PLC ORD 37.5P",
    "percentageChange": -0.42,
    "marketCap": 7793440000
  },
  {
    "name": "PERSHING SQUARE HOLDINGS LTD ORD NPV",
    "percentageChange": -0.14,
    "marketCap": 7665630000
  },
  {
    "name": "MELROSE INDUSTRIES PLC ORD GBP0.001",
    "percentageChange": -0.24,
    "marketCap": 7486390000
  },
  {
    "name": "INTERTEK GROUP PLC ORD 1P",
    "percentageChange": -0.88,
    "marketCap": 7437720000
  },
  {
    "name": "MARKS & SPENCER GROUP PLC ORD 1P",
    "percentageChange": -0.14,
    "marketCap": 7372080000
  },
  {
    "name": "DIPLOMA PLC ORD 5P",
    "percentageChange": 0.28,
    "marketCap": 7285770000
  },
  {
    "name": "AUTO TRADER GROUP PLC ORD 1P",
    "percentageChange": -0.49,
    "marketCap": 7194520000
  },
  {
    "name": "PEARSON PLC ORD 25P",
    "percentageChange": -0.23,
    "marketCap": 7105000000
  },
  {
    "name": "SAINSBURY(J) PLC ORD 28 4/7P",
    "percentageChange": 0.46,
    "marketCap": 6973190000
  },
  {
    "name": "ST.JAMES'S PLACE PLC ORD 15P",
    "percentageChange": -1.03,
    "marketCap": 6971150000
  },
  {
    "name": "PHOENIX GROUP HOLDINGS PLC ORD 10P",
    "percentageChange": -0.22,
    "marketCap": 6970770000
  },
  {
    "name": "WEIR GROUP PLC ORD 12.5P",
    "percentageChange": -1.83,
    "marketCap": 6521450000
  },
  {
    "name": "M&G PLC ORD £0.05",
    "percentageChange": -0.41,
    "marketCap": 6449980000
  },
  {
    "name": "ICG PLC ORD 26 1/4P",
    "percentageChange": -2.08,
    "marketCap": 6417290000
  },
  {
    "name": "SCHRODERS PLC ORD 20P",
    "percentageChange": -2.57,
    "marketCap": 6388080000
  },
  {
    "name": "ENDEAVOUR MINING PLC ORD USD0.01",
    "percentageChange": 1.33,
    "marketCap": 6164280000
  },
  {
    "name": "RIGHTMOVE  PLC ORD 0.1P",
    "percentageChange": -0.44,
    "marketCap": 5964990000
  },
  {
    "name": "IMI PLC ORD 28 4/7P",
    "percentageChange": -0.69,
    "marketCap": 5753940000
  },
  {
    "name": "ENTAIN PLC ORD EUR0.01",
    "percentageChange": -0.98,
    "marketCap": 5640780000
  },
  {
    "name": "F&C INVESTMENT TRUST PLC ORD 25P",
    "percentageChange": -0.68,
    "marketCap": 5615670000
  },
  {
    "name": "WHITBREAD PLC ORD 76 122/153P",
    "percentageChange": -2,
    "marketCap": 5573000000
  },
  {
    "name": "BARRATT REDROW PLC ORD 10P",
    "percentageChange": -1.5,
    "marketCap": 5442880000
  },
  {
    "name": "SPIRAX GROUP PLC ORD 26 12/13P",
    "percentageChange": -1.16,
    "marketCap": 5415160000
  },
  {
    "name": "GAMES WORKSHOP GROUP PLC ORD 5P",
    "percentageChange": -1.95,
    "marketCap": 5242520000
  },
  {
    "name": "BABCOCK INTERNATIONAL GROUP PLC ORD 60P",
    "percentageChange": 1.4,
    "marketCap": 5040750000
  },
  {
    "name": "ALLIANCE WITAN PLC ORD 2.5P",
    "percentageChange": -0.63,
    "marketCap": 5021270000
  },
  {
    "name": "CONVATEC GROUP PLC ORD 10P",
    "percentageChange": -2.88,
    "marketCap": 4976870000
  },
  {
    "name": "KINGFISHER PLC ORD 15 5/7P",
    "percentageChange": -4.3,
    "marketCap": 4922410000
  },
  {
    "name": "BEAZLEY PLC ORD 5P",
    "percentageChange": -0.51,
    "marketCap": 4863000000
  },
  {
    "name": "HOWDEN JOINERY GROUP PLC ORD 10P",
    "percentageChange": -1.42,
    "marketCap": 4794590000
  },
  {
    "name": "MONDI PLC ORD EUR 0.22",
    "percentageChange": -0.14,
    "marketCap": 4738560000
  },
  {
    "name": "JD SPORTS FASHION PLC ORD 0.05P",
    "percentageChange": -0.64,
    "marketCap": 4720270000
  },
  {
    "name": "DCC PLC ORD EUR0.25 (CDI)",
    "percentageChange": -1.98,
    "marketCap": 4714200000
  },
  {
    "name": "POLAR CAPITAL TECHNOLOGY TRUST PLC ORD 2.5P",
    "percentageChange": -0.38,
    "marketCap": 4542790000
  },
  {
    "name": "LONDONMETRIC PROPERTY PLC ORD 10P",
    "percentageChange": -0.42,
    "marketCap": 4498380000
  },
  {
    "name": "HISCOX LD ORD 6.5P (DI)",
    "percentageChange": -1.35,
    "marketCap": 4484060000
  },
  {
    "name": "WPP PLC ORD 10P",
    "percentageChange": -1.32,
    "marketCap": 4327080000
  },
  {
    "name": "LAND SECURITIES GROUP PLC ORD 10 2/3P",
    "percentageChange": -1.21,
    "marketCap": 4305790000
  },
  {
    "name": "HIKMA PHARMACEUTICALS PLC ORD SHS 10P",
    "percentageChange": null,
    "marketCap": 4073840000
  },
  {
    "name": "EASYJET PLC ORD 27 2/7P",
    "percentageChange": -1.02,
    "marketCap": 3870400000
  },
  {
    "name": "BERKELEY GROUP HOLDINGS (THE) PLC ORD 5.6110477936P",
    "percentageChange": -2.27,
    "marketCap": 3641830000
  },
  {
    "name": "PERSIMMON PLC ORD 10P",
    "percentageChange": -1.11,
    "marketCap": 3614800000
  },
  {
    "name": "UNITE GROUP PLC ORD 25P",
    "percentageChange": -1.16,
    "marketCap": 3599410000
  },
  {
    "name": "CRODA INTERNATIONAL PLC ORD 10.609756P",
    "percentageChange": 0.16,
    "marketCap": 3566290000
  },
  {
    "name": "TAYLOR WIMPEY PLC ORD 1P",
    "percentageChange": -0.95,
    "marketCap": 3566180000
  }
]